dbjudge/__init__.py
dbjudge/exceptions.py
dbjudge/fake_data_gen.py
dbjudge/filler.py
dbjudge/squema_recollector.py
dbjudge/type_compatible.py
dbjudge/connection_manager/__init__.py
dbjudge/connection_manager/manager.py
dbjudge/custom_fakes/__init__.py
dbjudge/custom_fakes/custom_generator.py
dbjudge/custom_fakes/custom_loader.py
dbjudge/judge/__init__.py
dbjudge/judge/judge.py
dbjudge/questions/__init__.py
dbjudge/questions/generation/__init__.py
dbjudge/questions/generation/constraints_truth_table.py
dbjudge/questions/generation/generator.py
dbjudge/questions/isolation/__init__.py
dbjudge/questions/isolation/analyzer.py
dbjudge/questions/isolation/slicer.py
dbjudge/structures/__init__.py
dbjudge/structures/column.py
dbjudge/structures/context.py
dbjudge/structures/fake_types.py
dbjudge/structures/foreign_key.py
dbjudge/structures/reference.py
dbjudge/structures/table.py
dbjudge/utils/__init__.py
dbjudge/utils/metaclasses.py
dbjudge/utils/queries.py
dbjudge-1.0.0a3.dist-info/LICENSE.md
dbjudge-1.0.0a3.dist-info/METADATA
dbjudge-1.0.0a3.dist-info/WHEEL
dbjudge-1.0.0a3.dist-info/top_level.txt
dbjudge-1.0.0a3.dist-info/RECORD
