Metadata-Version: 2.1
Name: dbjudge
Version: 1.0.0a3
Summary: A SQL judge for postgresql
Home-page: UNKNOWN
Author: Raúl Medina González
Author-email: raulmgcontact@gmail.com
License: UNKNOWN
Platform: UNKNOWN
Requires-Dist: psycopg2
Requires-Dist: xeger
Requires-Dist: sqlparse
